{
    "development": {
        "environment": "development",
        "debug": true,
        "logLevel": "debug",
        "apiTimeout": 10000,
        "enableMockData": true,
        "skipValidation": false,
        "enablePerformanceTracking": true,
        "supabase": {
            "enableCloudSync": true,
            "autoSync": false,
            "syncInterval": 60000,
            "maxRetries": 5,
            "enableBackups": true
        },
        "features": {
            "analytics": false,
            "telemetry": false,
            "errorReporting": true,
            "betaFeatures": true,
            "advancedLogging": true
        },
        "blocklists": {
            "updateInterval": 300000,
            "enableCache": true,
            "maxConcurrentFetches": 5,
            "enableValidation": true
        },
        "ui": {
            "enableAnimations": true,
            "showDebugInfo": true,
            "enableTooltips": true,
            "theme": "auto"
        }
    },
    "staging": {
        "environment": "staging",
        "debug": true,
        "logLevel": "info",
        "apiTimeout": 15000,
        "enableMockData": false,
        "skipValidation": false,
        "enablePerformanceTracking": true,
        "supabase": {
            "enableCloudSync": true,
            "autoSync": true,
            "syncInterval": 300000,
            "maxRetries": 3,
            "enableBackups": true
        },
        "features": {
            "analytics": true,
            "telemetry": false,
            "errorReporting": true,
            "betaFeatures": true,
            "advancedLogging": false
        },
        "blocklists": {
            "updateInterval": 3600000,
            "enableCache": true,
            "maxConcurrentFetches": 3,
            "enableValidation": true
        },
        "ui": {
            "enableAnimations": true,
            "showDebugInfo": false,
            "enableTooltips": true,
            "theme": "auto"
        }
    },
    "production": {
        "environment": "production",
        "debug": false,
        "logLevel": "warn",
        "apiTimeout": 30000,
        "enableMockData": false,
        "skipValidation": false,
        "enablePerformanceTracking": false,
        "supabase": {
            "enableCloudSync": true,
            "autoSync": true,
            "syncInterval": 300000,
            "maxRetries": 3,
            "enableBackups": true
        },
        "features": {
            "analytics": false,
            "telemetry": false,
            "errorReporting": true,
            "betaFeatures": false,
            "advancedLogging": false
        },
        "blocklists": {
            "updateInterval": 86400000,
            "enableCache": true,
            "maxConcurrentFetches": 2,
            "enableValidation": true
        },
        "ui": {
            "enableAnimations": true,
            "showDebugInfo": false,
            "enableTooltips": true,
            "theme": "auto"
        },
        "security": {
            "enableCSP": true,
            "requireHttps": true,
            "enableHSTS": true,
            "maxSessionAge": 86400000
        },
        "performance": {
            "enableCompression": true,
            "enableCaching": true,
            "maxCacheSize": 50000000,
            "enableMinification": true
        }
    },
    "testing": {
        "environment": "testing",
        "debug": true,
        "logLevel": "debug",
        "apiTimeout": 5000,
        "enableMockData": true,
        "skipValidation": true,
        "enablePerformanceTracking": false,
        "supabase": {
            "enableCloudSync": false,
            "autoSync": false,
            "syncInterval": 0,
            "maxRetries": 1,
            "enableBackups": false
        },
        "features": {
            "analytics": false,
            "telemetry": false,
            "errorReporting": false,
            "betaFeatures": true,
            "advancedLogging": true
        },
        "blocklists": {
            "updateInterval": 0,
            "enableCache": false,
            "maxConcurrentFetches": 1,
            "enableValidation": false
        },
        "ui": {
            "enableAnimations": false,
            "showDebugInfo": true,
            "enableTooltips": false,
            "theme": "light"
        }
    }
}